pyg_timeseries/__init__.py
pyg_timeseries/_autotrend.py
pyg_timeseries/_bar.py
pyg_timeseries/_decorators.py
pyg_timeseries/_ewm.py
pyg_timeseries/_ewmcombine.py
pyg_timeseries/_ewmxo.py
pyg_timeseries/_expanding.py
pyg_timeseries/_iter.py
pyg_timeseries/_linalg.py
pyg_timeseries/_math.py
pyg_timeseries/_matmul.py
pyg_timeseries/_max.py
pyg_timeseries/_maxdiv.py
pyg_timeseries/_median.py
pyg_timeseries/_min.py
pyg_timeseries/_multibuffer.py
pyg_timeseries/_opt.py
pyg_timeseries/_pandas.py
pyg_timeseries/_rank.py
pyg_timeseries/_riskparity.py
pyg_timeseries/_rms_join.py
pyg_timeseries/_rolling.py
pyg_timeseries/_stride.py
pyg_timeseries/_track.py
pyg_timeseries/_ts.py
pyg_timeseries/_xrank.py
pyg_timeseries/_zmooth.py
pyg_timeseries-0.0.42.dist-info/licenses/LICENSE.txt
pyg_timeseries-0.0.42.dist-info/METADATA
pyg_timeseries-0.0.42.dist-info/WHEEL
pyg_timeseries-0.0.42.dist-info/top_level.txt
pyg_timeseries-0.0.42.dist-info/RECORD
