Metadata-Version: 2.4
Name: pyg-timeseries
Version: 0.0.42
Summary: Utilities for fast timeseries analysis
Home-page: https://github.com/gityoav/pyg-timeseries
Author: Yoav Git
Author-email: yoav.git@gmail.com
Project-URL: Bug Tracker, https://github.com/gityoav/pyg-timeseries/issues
Classifier: Programming Language :: Python :: 3
Classifier: License :: OSI Approved :: GNU General Public License v3 (GPLv3)
Classifier: Operating System :: OS Independent
Requires-Python: >=3.6
License-File: LICENSE.txt
Requires-Dist: pyg-base
Requires-Dist: numba
Requires-Dist: bottleneck
Dynamic: license-file
